{
  "speedCameraDistance": 100,
  "speedCameraWidth": 15,
  "speedLimits": {
    "2896128334": 65,
    "2552845347": 65,
    "776581733": 65,
    "2600585507": 65,
    "3362327680": 65,
    "302348953": 65,
    "4124992785": 65,
    "3436239235": 35,
    "3168230186": 35,
    "127506487": 35,
    "3474613771": 35,
    "3885181515": 65,
    "1759459593": 35,
    "2226519225": 35,
    "127435642": 35,
    "4155137": 35,
    "4174973413": 35,
    "2502989037": 35,
    "2464268432": 35
  },
  "speedCameras": [
    {
      "width": 10.0,
      "start": {
        "X": 770.918457,
        "Y": -708.5312,
        "Z": 27.4736938
      },
      "end": {
        "X": 770.7792,
        "Y": -724.9011,
        "Z": 30.0247421
      }
    },
    {
      "width": 10.0,
      "start": {
        "X": 781.278748,
        "Y": -724.783264,
        "Z": 27.0532837
      },
      "end": {
        "X": 781.7012,
        "Y": -709.529663,
        "Z": 30.4116554
      }
    },
    {
      "width": 10.0,
      "start": {
        "X": 796.310059,
        "Y": -1097.6062,
        "Z": 27.8202877
      },
      "end": {
        "X": 794.5419,
        "Y": -1079.88867,
        "Z": 30.6000881
      }
    },
    {
      "width": 10.0,
      "start": {
        "X": 783.846863,
        "Y": -1080.91943,
        "Z": 27.6553688
      },
      "end": {
        "X": 785.6039,
        "Y": -1098.71777,
        "Z": 30.856472
      }
    },
    {
      "width": 10.0,
      "start": {
        "X": 833.0685,
        "Y": -1804.2229,
        "Z": 28.129385
      },
      "end": {
        "X": 836.046265,
        "Y": -1781.86157,
        "Z": 31.1367035
      }
    },
    {
      "width": 10.0,
      "start": {
        "X": 803.315552,
        "Y": -1836.32385,
        "Z": 28.4136486
      },
      "end": {
        "X": 800.2155,
        "Y": -1853.38232,
        "Z": 31.3487225
      }
    },
    {
      "width": 10.0,
      "start": {
        "X": 792.0123,
        "Y": -2024.03711,
        "Z": 28.331749
      },
      "end": {
        "X": 794.936951,
        "Y": -2000.494,
        "Z": 31.3322
      }
    },
    {
      "width": 10.0,
      "start": {
        "X": 756.9607,
        "Y": -2134.54126,
        "Z": 28.3477058
      },
      "end": {
        "X": 755.612732,
        "Y": -2152.28687,
        "Z": 31.3364372
      }
    },
    {
      "width": 10.0,
      "start": {
        "X": 741.9586,
        "Y": -2949.69775,
        "Z": 4.80071831
      },
      "end": {
        "X": 741.851868,
        "Y": -2925.47559,
        "Z": 7.830374
      }
    },
    {
      "width": 10.0,
      "start": {
        "X": 727.4114,
        "Y": -2925.985,
        "Z": 5.0038147
      },
      "end": {
        "X": 726.7536,
        "Y": -2950.47559,
        "Z": 8.523418
      }
    },
    {
      "width": 10.0,
      "start": {
        "X": 712.9739,
        "Y": -2970.66479,
        "Z": 5.254938
      },
      "end": {
        "X": 711.330566,
        "Y": -2993.544,
        "Z": 8.255041
      }
    },
    {
      "width": 10.0,
      "start": {
        "X": 984.8905,
        "Y": -3326.16,
        "Z": 5.179079
      },
      "end": {
        "X": 1012.56659,
        "Y": -3325.99414,
        "Z": 7.927644
      }
    },
    {
      "width": 10.0,
      "start": {
        "X": 658.0995,
        "Y": -179.718781,
        "Z": 45.5322647
      },
      "end": {
        "X": 648.556335,
        "Y": -195.279022,
        "Z": 47.4670067
      }
    },
    {
      "width": 10.0,
      "start": {
        "X": 658.7205,
        "Y": -201.134644,
        "Z": 44.31493
      },
      "end": {
        "X": 648.3401,
        "Y": -218.34491,
        "Z": 46.0406952
      }
    },
    {
      "width": 10.0,
      "start": {
        "X": 660.489441,
        "Y": -229.973755,
        "Z": 42.7261543
      },
      "end": {
        "X": 672.8049,
        "Y": -209.939117,
        "Z": 46.73763
      }
    },
    {
      "width": 10.0,
      "start": {
        "X": 1089.17163,
        "Y": 369.388031,
        "Z": 82.08873
      },
      "end": {
        "X": 1107.18494,
        "Y": 388.438721,
        "Z": 85.47342
      }
    },
    {
      "width": 10.0,
      "start": {
        "X": 1152.31067,
        "Y": 457.2893,
        "Z": 81.73668
      },
      "end": {
        "X": 1133.57263,
        "Y": 438.4027,
        "Z": 85.3605652
      }
    },
    {
      "width": 10.0,
      "start": {
        "X": 1056.12378,
        "Y": 305.013947,
        "Z": 86.33548
      },
      "end": {
        "X": 1072.42236,
        "Y": 315.348969,
        "Z": 91.35254
      }
    },
    {
      "width": 10.0,
      "start": {
        "X": 1178.09119,
        "Y": 507.9802,
        "Z": 83.5728455
      },
      "end": {
        "X": 1166.98828,
        "Y": 499.785828,
        "Z": 88.54759
      }
    },
    {
      "width": 10.0,
      "start": {
        "X": 1739.57837,
        "Y": 1521.64929,
        "Z": 83.66508
      },
      "end": {
        "X": 1746.81921,
        "Y": 1540.97388,
        "Z": 86.62971
      }
    },
    {
      "width": 10.0,
      "start": {
        "X": 2326.379,
        "Y": 2803.39966,
        "Z": 40.79667
      },
      "end": {
        "X": 2345.89844,
        "Y": 2814.54614,
        "Z": 44.459446
      }
    },
    {
      "width": 25.0,
      "start": {
        "X": 2321.28857,
        "Y": 2823.22949,
        "Z": 40.3829651
      },
      "end": {
        "X": 2353.52051,
        "Y": 2847.35913,
        "Z": 42.68192
      }
    },
    {
      "width": 25.0,
      "start": {
        "X": 2450.4043,
        "Y": 2958.183,
        "Z": 39.72705
      },
      "end": {
        "X": 2483.90332,
        "Y": 2987.15942,
        "Z": 43.27803
      }
    },
    {
      "width": 10.0,
      "start": {
        "X": 2504.638,
        "Y": 3026.0752,
        "Z": 41.3209267
      },
      "end": {
        "X": 2489.79272,
        "Y": 3016.91772,
        "Z": 44.19594
      }
    },
    {
      "width": 10.0,
      "start": {
        "X": 2556.96362,
        "Y": 543.365234,
        "Z": 107.472183
      },
      "end": {
        "X": 2560.1167,
        "Y": 520.4874,
        "Z": 109.993927
      }
    },
    {
      "width": 10.0,
      "start": {
        "X": 2531.75659,
        "Y": 543.2142,
        "Z": 111.198341
      },
      "end": {
        "X": 2533.10718,
        "Y": 523.4095,
        "Z": 114.947113
      }
    },
    {
      "width": 10.0,
      "start": {
        "X": 2601.34766,
        "Y": 234.237885,
        "Z": 97.3145142
      },
      "end": {
        "X": 2607.313,
        "Y": 261.744415,
        "Z": 100.207916
      }
    },
    {
      "width": 10.0,
      "start": {
        "X": 2589.91455,
        "Y": 242.951523,
        "Z": 102.125183
      },
      "end": {
        "X": 2594.64,
        "Y": 265.924866,
        "Z": 106.817764
      }
    },
    {
      "width": 10.0,
      "start": {
        "X": 1263.2373,
        "Y": -1140.729,
        "Z": 50.60892
      },
      "end": {
        "X": 1248.70691,
        "Y": -1146.79871,
        "Z": 53.627
      }
    },
    {
      "width": 10.0,
      "start": {
        "X": 1255.14,
        "Y": -1161.86768,
        "Z": 51.2373772
      },
      "end": {
        "X": 1269.2417,
        "Y": -1156.18127,
        "Z": 53.36693
      }
    },
    {
      "width": 10.0,
      "start": {
        "X": 1235.99377,
        "Y": -1187.27075,
        "Z": 47.0852051
      },
      "end": {
        "X": 1251.01111,
        "Y": -1181.33459,
        "Z": 51.2000046
      }
    },
    {
      "width": 10.0,
      "start": {
        "X": 1184.532,
        "Y": -1150.582,
        "Z": 44.8524246
      },
      "end": {
        "X": 1160.11682,
        "Y": -1153.58826,
        "Z": 46.4418335
      }
    },
    {
      "width": 10.0,
      "start": {
        "X": 1065.64307,
        "Y": -995.574463,
        "Z": 31.3710518
      },
      "end": {
        "X": 1062.17859,
        "Y": -983.5831,
        "Z": 33.6041336
      }
    },
    {
      "width": 10.0,
      "start": {
        "X": 1016.23004,
        "Y": -945.788,
        "Z": 29.3566113
      },
      "end": {
        "X": 1021.81024,
        "Y": -964.4811,
        "Z": 32.3219681
      }
    },
    {
      "width": 10.0,
      "start": {
        "X": 1000.42993,
        "Y": -950.451355,
        "Z": 29.4917374
      },
      "end": {
        "X": 1005.68372,
        "Y": -968.155151,
        "Z": 32.58835
      }
    },
    {
      "width": 10.0,
      "start": {
        "X": 1037.80066,
        "Y": -959.582458,
        "Z": 29.4572945
      },
      "end": {
        "X": 1032.42261,
        "Y": -941.2667,
        "Z": 32.2535973
      }
    },
    {
      "width": 10.0,
      "start": {
        "X": 1054.20923,
        "Y": -955.372131,
        "Z": 29.5899467
      },
      "end": {
        "X": 1048.206,
        "Y": -936.1304,
        "Z": 32.4196854
      }
    },
    {
      "width": 20.0,
      "start": {
        "X": 807.7168,
        "Y": -675.5619,
        "Z": 40.4616
      },
      "end": {
        "X": 823.9432,
        "Y": -686.279236,
        "Z": 44.3140869
      }
    },
    {
      "width": 20.0,
      "start": {
        "X": 840.0606,
        "Y": -662.4706,
        "Z": 41.6302147
      },
      "end": {
        "X": 823.095764,
        "Y": -651.1566,
        "Z": 43.72985
      }
    },
    {
      "width": 20.0,
      "start": {
        "X": -1616.52075,
        "Y": -724.4994,
        "Z": 10.3323889
      },
      "end": {
        "X": -1633.37354,
        "Y": -716.303345,
        "Z": 13.2200975
      }
    },
    {
      "width": 17.0,
      "start": {
        "X": -1642.31921,
        "Y": -733.332764,
        "Z": 10.4398212
      },
      "end": {
        "X": -1623.291,
        "Y": -742.911133,
        "Z": 13.4133968
      }
    },
    {
      "width": 12.0,
      "start": {
        "X": -1652.13354,
        "Y": -747.963257,
        "Z": 9.24025
      },
      "end": {
        "X": -1634.99,
        "Y": -761.2546,
        "Z": 12.3390465
      }
    },
    {
      "width": 12.0,
      "start": {
        "X": -1659.68457,
        "Y": -757.1665,
        "Z": 9.145691
      },
      "end": {
        "X": -1643.562,
        "Y": -770.894531,
        "Z": 11.961792
      }
    },
    {
      "width": 12.0,
      "start": {
        "X": -2431.54785,
        "Y": -229.611877,
        "Z": 15.2956047
      },
      "end": {
        "X": -2450.085,
        "Y": -219.806458,
        "Z": 18.9032
      }
    },
    {
      "width": 12.0,
      "start": {
        "X": -2510.306,
        "Y": -205.7956,
        "Z": 17.7061958
      },
      "end": {
        "X": -2491.79126,
        "Y": -215.224442,
        "Z": 20.0794621
      }
    },
    {
      "width": 20.0,
      "start": {
        "X": 206.321533,
        "Y": -1044.53918,
        "Z": 28.2972565
      },
      "end": {
        "X": 219.266632,
        "Y": -1049.55994,
        "Z": 31.3241711
      }
    },
    {
      "width": 20.0,
      "start": {
        "X": 220.561172,
        "Y": -1026.02014,
        "Z": 28.3740177
      },
      "end": {
        "X": 217.095139,
        "Y": -1035.39429,
        "Z": 31.3601913
      }
    },
    {
      "width": 20.0,
      "start": {
        "X": 226.186676,
        "Y": -1059.61816,
        "Z": 28.15083
      },
      "end": {
        "X": 229.395279,
        "Y": -1048.40259,
        "Z": 31.33398
      }
    },
    {
      "width": 20.0,
      "start": {
        "X": 239.666336,
        "Y": -1041.00439,
        "Z": 28.3818779
      },
      "end": {
        "X": 228.43074,
        "Y": -1036.75562,
        "Z": 31.3352585
      }
    },
    {
      "width": 12.0,
      "start": {
        "X": 435.434753,
        "Y": -1040.21838,
        "Z": 29.74561
      },
      "end": {
        "X": 423.865631,
        "Y": -1041.574,
        "Z": 31.969408
      }
    },
    {
      "width": 12.0,
      "start": {
        "X": 422.7752,
        "Y": -1052.58862,
        "Z": 28.8298416
      },
      "end": {
        "X": 434.50592,
        "Y": -1051.13135,
        "Z": 32.57868
      }
    },
    {
      "width": 12.0,
      "start": {
        "X": 733.9805,
        "Y": -1014.2088,
        "Z": 27.2428741
      },
      "end": {
        "X": 746.4131,
        "Y": -1012.63812,
        "Z": 28.92767
      }
    },
    {
      "width": 12.0,
      "start": {
        "X": 744.8455,
        "Y": -1002.30389,
        "Z": 25.98454
      },
      "end": {
        "X": 733.2053,
        "Y": -1003.43329,
        "Z": 30.2107944
      }
    },
    {
      "width": 12.0,
      "start": {
        "X": 582.342834,
        "Y": -1021.98688,
        "Z": 36.13409
      },
      "end": {
        "X": 570.0058,
        "Y": -1023.6217,
        "Z": 39.043354
      }
    },
    {
      "width": 12.0,
      "start": {
        "X": 583.216736,
        "Y": -1032.6759,
        "Z": 36.13479
      },
      "end": {
        "X": 595.338562,
        "Y": -1031.21216,
        "Z": 39.03881
      }
    },
    {
      "width": 12.0,
      "start": {
        "X": 587.073,
        "Y": -394.754669,
        "Z": 42.72322
      },
      "end": {
        "X": 593.294067,
        "Y": -381.53006,
        "Z": 45.676
      }
    },
    {
      "width": 10.0,
      "start": {
        "X": 1022.9599,
        "Y": 480.91333,
        "Z": 95.2236252
      },
      "end": {
        "X": 1036.02161,
        "Y": 495.265259,
        "Z": 98.10761
      }
    },
    {
      "width": 10.0,
      "start": {
        "X": 1032.21179,
        "Y": 499.38028,
        "Z": 95.5450745
      },
      "end": {
        "X": 1017.44891,
        "Y": 485.0855,
        "Z": 98.7671661
      }
    },
    {
      "width": 10.0,
      "start": {
        "X": 1468.69519,
        "Y": 749.6573,
        "Z": 76.45197
      },
      "end": {
        "X": 1488.2218,
        "Y": 771.4511,
        "Z": 79.4670639
      }
    },
    {
      "width": 10.0,
      "start": {
        "X": 1552.9823,
        "Y": 880.0612,
        "Z": 76.468
      },
      "end": {
        "X": 1558.65137,
        "Y": 897.4771,
        "Z": 79.45197
      }
    },
    {
      "width": 10.0,
      "start": {
        "X": 2026.56458,
        "Y": 2580.246,
        "Z": 53.5150146
      },
      "end": {
        "X": 2038.97888,
        "Y": 2592.37134,
        "Z": 56.090538
      }
    },
    {
      "width": 10.0,
      "start": {
        "X": 2035.804,
        "Y": 2571.77612,
        "Z": 53.5346069
      },
      "end": {
        "X": 2047.18164,
        "Y": 2582.74854,
        "Z": 56.15004
      }
    },
    {
      "width": 10.0,
      "start": {
        "X": 1995.72729,
        "Y": 2573.51953,
        "Z": 53.6272278
      },
      "end": {
        "X": 1982.32031,
        "Y": 2559.33643,
        "Z": 56.67443
      }
    },
    {
      "width": 10.0,
      "start": {
        "X": 1986.7489,
        "Y": 2582.18359,
        "Z": 53.5301056
      },
      "end": {
        "X": 1972.90259,
        "Y": 2568.627,
        "Z": 56.575367
      }
    },
    {
      "width": 10.0,
      "limit": 35,
      "start": {
        "X": -362.977966,
        "Y": 6025.393,
        "Z": 30.269474
      },
      "end": {
        "X": -377.061859,
        "Y": 6010.64063,
        "Z": 33.35479
      }
    },
    {
      "width": 10.0,
      "limit": 35,
      "start": {
        "X": -369.704346,
        "Y": 6002.081,
        "Z": 30.3473969
      },
      "end": {
        "X": -355.9171,
        "Y": 6016.545,
        "Z": 33.20292
      }
    },
    {
      "width": 10.0,
      "limit": 35,
      "start": {
        "X": -284.78717,
        "Y": 6083.471,
        "Z": 30.2266922
      },
      "end": {
        "X": -275.1366,
        "Y": 6092.92041,
        "Z": 33.2230072
      }
    },
    {
      "width": 10.0,
      "limit": 35,
      "start": {
        "X": -283.248016,
        "Y": 6101.571,
        "Z": 30.219347
      },
      "end": {
        "X": -292.041046,
        "Y": 6092.497,
        "Z": 33.1974678
      }
    },
    {
      "width": 10.0,
      "limit": 35,
      "start": {
        "X": -111.91478,
        "Y": 6274.956,
        "Z": 30.21454
      },
      "end": {
        "X": -124.054794,
        "Y": 6262.944,
        "Z": 33.1832733
      }
    },
    {
      "width": 10.0,
      "limit": 35,
      "start": {
        "X": -117.01339,
        "Y": 6256.03955,
        "Z": 30.159647
      },
      "end": {
        "X": -103.828842,
        "Y": 6267.15625,
        "Z": 33.3091621
      }
    },
    {
      "width": 10.0,
      "limit": 35,
      "start": {
        "X": 135.705414,
        "Y": 6520.311,
        "Z": 30.6020145
      },
      "end": {
        "X": 124.843147,
        "Y": 6510.804,
        "Z": 33.5202827
      }
    },
    {
      "width": 10.0,
      "limit": 35,
      "start": {
        "X": 131.79097,
        "Y": 6503.93457,
        "Z": 30.4551544
      },
      "end": {
        "X": 141.338287,
        "Y": 6512.07471,
        "Z": 33.5165672
      }
    },
    {
      "width": 15.0,
      "start": {
        "X": 1021.10889,
        "Y": 6491.46045,
        "Z": 19.9819241
      },
      "end": {
        "X": 1003.55341,
        "Y": 6491.71875,
        "Z": 22.9763565
      }
    },
    {
      "width": 10.0,
      "start": {
        "X": 1032.52551,
        "Y": 6481.307,
        "Z": 19.9934311
      },
      "end": {
        "X": 1045.61572,
        "Y": 6481.3125,
        "Z": 23.006752
      }
    },
    {
      "width": 15.0,
      "start": {
        "X": 1936.60132,
        "Y": 6257.47559,
        "Z": 42.4075279
      },
      "end": {
        "X": 1943.07275,
        "Y": 6243.05469,
        "Z": 45.8330841
      }
    },
    {
      "width": 15.0,
      "start": {
        "X": 2049.37573,
        "Y": 6144.064,
        "Z": 48.1488647
      },
      "end": {
        "X": 2035.69177,
        "Y": 6159.564,
        "Z": 50.6003838
      }
    },
    {
      "width": 15.0,
      "start": {
        "X": 2524.352,
        "Y": 5423.81738,
        "Z": 43.5598373
      },
      "end": {
        "X": 2530.88721,
        "Y": 5400.8916,
        "Z": 46.56208
      }
    },
    {
      "width": 15.0,
      "start": {
        "X": 2571.72827,
        "Y": 5357.1377,
        "Z": 43.5772247
      },
      "end": {
        "X": 2565.07715,
        "Y": 5380.07129,
        "Z": 46.56473
      }
    },
    {
      "width": 10.0,
      "start": {
        "X": 2642.242,
        "Y": 4331.91162,
        "Z": 43.6642075
      },
      "end": {
        "X": 2627.884,
        "Y": 4315.85352,
        "Z": 46.0439
      }
    },
    {
      "width": 10.0,
      "start": {
        "X": 2599.08228,
        "Y": 4270.70752,
        "Z": 41.5992775
      },
      "end": {
        "X": 2611.889,
        "Y": 4287.89453,
        "Z": 45.1643143
      }
    },
    {
      "width": 10.0,
      "start": {
        "X": 1878.63672,
        "Y": 3617.65381,
        "Z": 33.37136
      },
      "end": {
        "X": 1859.95044,
        "Y": 3606.77075,
        "Z": 36.666275
      }
    },
    {
      "width": 10.0,
      "start": {
        "X": 1826.22266,
        "Y": 3580.51831,
        "Z": 34.23941
      },
      "end": {
        "X": 1843.52991,
        "Y": 3590.78931,
        "Z": 36.96878
      }
    },
    {
      "width": 10.0,
      "start": {
        "X": 1709.697,
        "Y": 3582.29761,
        "Z": 34.51953
      },
      "end": {
        "X": 1694.5542,
        "Y": 3573.4873,
        "Z": 37.605835
      }
    },
    {
      "width": 10.0,
      "start": {
        "X": 1696.286,
        "Y": 3569.11987,
        "Z": 34.6140938
      },
      "end": {
        "X": 1711.95288,
        "Y": 3578.46948,
        "Z": 37.5316238
      }
    },
    {
      "width": 10.0,
      "start": {
        "X": 1874.74084,
        "Y": 3677.2583,
        "Z": 32.6291237
      },
      "end": {
        "X": 1864.5542,
        "Y": 3671.29663,
        "Z": 35.8675079
      }
    },
    {
      "width": 10.0,
      "start": {
        "X": 1829.5376,
        "Y": 3645.072,
        "Z": 33.31183
      },
      "end": {
        "X": 1837.52014,
        "Y": 3649.69214,
        "Z": 36.2859268
      }
    },
    {
      "width": 10.0,
      "start": {
        "X": -2562.09521,
        "Y": 3402.13745,
        "Z": 12.2227116
      },
      "end": {
        "X": -2567.971,
        "Y": 3377.26172,
        "Z": 15.3129482
      }
    },
    {
      "width": 10.0,
      "start": {
        "X": -2558.16479,
        "Y": 3375.11841,
        "Z": 12.3482552
      },
      "end": {
        "X": -2553.198,
        "Y": 3399.58423,
        "Z": 15.250412
      }
    },
    {
      "width": 10.0,
      "start": {
        "X": -2610.627,
        "Y": 2979.851,
        "Z": 15.6196938
      },
      "end": {
        "X": -2615.45947,
        "Y": 2948.15723,
        "Z": 18.6669426
      }
    },
    {
      "width": 10.0,
      "start": {
        "X": -2604.76978,
        "Y": 2946.30933,
        "Z": 15.7013283
      },
      "end": {
        "X": -2601.22119,
        "Y": 2976.97241,
        "Z": 18.6616249
      }
    }
  ]
}
